base64.py
setup.py
micropython_base64.egg-info/PKG-INFO
micropython_base64.egg-info/SOURCES.txt
micropython_base64.egg-info/dependency_links.txt
micropython_base64.egg-info/top_level.txt